tests/__init__.py
tests/integration/__init__.py
tests/integration/test_UF2_vs_RKE.py
tests/integration/test_linear_absorption.py
tests/integration/test_uf2.py
tests/integration/test_vs_matlab_code.py
tests/unit/__init__.py
ufss/RKE_core.py
ufss/RKE_open_core.py
ufss/UF2_core.py
ufss/UF2_open_core.py
ufss/__init__.py
ufss/convergence_tester.py
ufss/diagram_automation.py
ufss/dipole_pruning.py
ufss/efield_shapes.py
ufss/heaviside_convolve.py
ufss/HLG/DiabaticLindblad_Liouvillians.py
ufss/HLG/Hamiltonians.py
ufss/HLG/Redfield_Liouvillians.py
ufss/HLG/__init__.py
ufss/HLG/base_class.py
ufss/HLG/dipole_operator.py
ufss/HLG/eigen_generator.py
ufss/HLG/eigenstates.py
ufss/HLG/general_Liouvillian_classes.py
ufss/HLG/manual_L_input.py
ufss/HLG/params_converter.py
ufss/HLG/run_HLG.py
ufss/HLG/simple_eigen_generator.py
ufss/RKE/RKE_core.py
ufss/RKE/RKE_open_core.py
ufss/RKE/__init__.py
ufss/UF2/UF2_core.py
ufss/UF2/UF2_open_core.py
ufss/UF2/__init__.py
ufss/UF2/heaviside_convolve.py
ufss/signals/__init__.py
ufss/signals/isotropic_averaging.py
ufss/signals/plotting_tools.py
ufss/signals/signal_processing.py
ufss/vibronic_eigenstates/Lindblad_eigenstates.py
ufss/vibronic_eigenstates/__init__.py
ufss/vibronic_eigenstates/base_class.py
ufss/vibronic_eigenstates/dipole_operator.py
ufss/vibronic_eigenstates/eigen_generator.py
ufss/vibronic_eigenstates/eigenstates.py
ufss/vibronic_eigenstates/manual_L_input.py
ufss/vibronic_eigenstates/params_converter.py
ufss/vibronic_eigenstates/simple_eigen_generator.py
ufss-0.1.2.dist-info/LICENSE
ufss-0.1.2.dist-info/METADATA
ufss-0.1.2.dist-info/WHEEL
ufss-0.1.2.dist-info/top_level.txt
ufss-0.1.2.dist-info/RECORD
