Metadata-Version: 2.1
Name: ufss
Version: 0.1.2
Summary: Package for simulating nonlinear optical spectra
Home-page: https://github.com/peterarose/ufss/
Author: Peter A. Rose and Jacob J. Krich
Author-email: peter.rose56@gmail.com
Keywords: n,o,n,l,i,n,e,a,r, ,o,p,t,i,c,a,l, ,s,p,e,c,t,r,o,s,c,o,p,y
Classifier: Development Status :: 3 - Alpha
Classifier: Intended Audience :: Science/Research
Classifier: Topic :: Scientific/Engineering :: Physics
Classifier: License :: OSI Approved :: MIT License
Classifier: Programming Language :: Python :: 3 :: Only
Requires-Python: >=3.5
License-File: LICENSE
Requires-Dist: numpy
Requires-Dist: matplotlib
Requires-Dist: pyfftw
Requires-Dist: scipy (>=1)
Requires-Dist: pyyaml
Requires-Dist: pyx
